[
  {
    "fold": 0,
    "method": "op",
    "di": 0.3926558117108485,
    "spd": 0.2554149446464922,
    "p_max": 0.42054398407265453,
    "p_min": 0.1651290394261623,
    "time_sec": 0.19632434844970703,
    "most_favored_group": {
      "race_White": [
        "==",
        1
      ],
      "sex": [
        "!=",
        1
      ]
    },
    "least_favored_group": {
      "race_Other": [
        "==",
        1
      ],
      "sex": [
        "==",
        1
      ]
    },
    "eo_di_y1_y0": [
      0.4360518144108724,
      0.3783373554794193
    ],
    "eo_spd_y1_y0": [
      0.26291107236910327,
      0.2510475104974932
    ],
    "eo_time_sec": 0.33797383308410645
  },
  {
    "fold": 1,
    "method": "op",
    "di": 0.7753676654677757,
    "spd": 0.07075586642186399,
    "p_max": 0.314985224941932,
    "p_min": 0.244229358520068,
    "time_sec": 0.2363758087158203,
    "most_favored_group": {
      "race_Asian-Pac-Islander": [
        "==",
        1
      ],
      "sex": [
        "!=",
        1
      ]
    },
    "least_favored_group": {
      "race_Amer-Indian-Eskimo": [
        "==",
        1
      ],
      "sex": [
        "==",
        1
      ]
    },
    "eo_di_y1_y0": [
      0.760545631855338,
      0.7808325655950388
    ],
    "eo_spd_y1_y0": [
      0.08573363645439996,
      0.06617098748480002
    ],
    "eo_time_sec": 0.41485595703125
  },
  {
    "fold": 2,
    "method": "op",
    "di": 0.6337074868864124,
    "spd": 0.1433410967954793,
    "p_max": 0.39132958404484,
    "p_min": 0.24798848724936068,
    "time_sec": 0.2052900791168213,
    "most_favored_group": {
      "race_White": [
        "==",
        1
      ],
      "sex": [
        "!=",
        1
      ]
    },
    "least_favored_group": {
      "race_Amer-Indian-Eskimo": [
        "==",
        1
      ],
      "sex": [
        "==",
        1
      ]
    },
    "eo_di_y1_y0": [
      0.8120732355333038,
      0.6230734644866213
    ],
    "eo_spd_y1_y0": [
      0.08103606981881145,
      0.1427460867267013
    ],
    "eo_time_sec": 0.37279510498046875
  },
  {
    "fold": 3,
    "method": "op",
    "di": 0.7814511506381477,
    "spd": 0.071141538384,
    "p_max": 0.325517789692,
    "p_min": 0.254376251308,
    "time_sec": 0.21240496635437012,
    "most_favored_group": {
      "race_Amer-Indian-Eskimo": [
        "==",
        1
      ],
      "sex": [
        "!=",
        1
      ]
    },
    "least_favored_group": {
      "race_Other": [
        "==",
        1
      ],
      "sex": [
        "==",
        1
      ]
    },
    "eo_di_y1_y0": [
      0.769928845778292,
      0.7873227416242717
    ],
    "eo_spd_y1_y0": [
      0.08563632394239995,
      0.06614758924800002
    ],
    "eo_time_sec": 0.3354508876800537
  },
  {
    "fold": 4,
    "method": "op",
    "di": 0.5654130693439866,
    "spd": 0.18011322652296755,
    "p_max": 0.4144469467848119,
    "p_min": 0.23433372026184437,
    "time_sec": 0.18741488456726074,
    "most_favored_group": {
      "race_Asian-Pac-Islander": [
        "==",
        1
      ],
      "sex": [
        "!=",
        1
      ]
    },
    "least_favored_group": {
      "race_Amer-Indian-Eskimo": [
        "==",
        1
      ],
      "sex": [
        "==",
        1
      ]
    },
    "eo_di_y1_y0": [
      0.6882396946928132,
      0.5579853687799422
    ],
    "eo_spd_y1_y0": [
      0.14254706336072398,
      0.17628305598086608
    ],
    "eo_time_sec": 0.35636281967163086
  }
]